fw_pyqt_management/__init__.py
fw_pyqt_management/adaptive_qt.py
fw_pyqt_management/config.py
fw_pyqt_management/fw_container_items.py
fw_pyqt_management/resources/config_defaults.json
fw_pyqt_management/resources/icons/Flywheel.icns
fw_pyqt_management/resources/icons/Flywheel.ico
fw_pyqt_management/resources/icons/Flywheel.png
fw_pyqt_management/resources/icons/acquisition.png
fw_pyqt_management/resources/icons/analysis.png
fw_pyqt_management/resources/icons/collection.png
fw_pyqt_management/resources/icons/download.png
fw_pyqt_management/resources/icons/dwnld-folder.png
fw_pyqt_management/resources/icons/file.png
fw_pyqt_management/resources/icons/file_cached.png
fw_pyqt_management/resources/icons/folder.png
fw_pyqt_management/resources/icons/group.png
fw_pyqt_management/resources/icons/project.png
fw_pyqt_management/resources/icons/session.png
fw_pyqt_management/resources/icons/subject.png
fw_pyqt_management/resources/paired_file_types.json
fw_pyqt_management/resources/required_modules.json
fw_pyqt_management/tree_management.py
fw_pyqt_management/utils.py
fw_pyqt_management-0.0.5.dist-info/LICENSE
fw_pyqt_management-0.0.5.dist-info/METADATA
fw_pyqt_management-0.0.5.dist-info/WHEEL
fw_pyqt_management-0.0.5.dist-info/RECORD
