Metadata-Version: 2.1
Name: fw-pyqt-management
Version: 0.0.5
Summary: A cross-platform PyQt Library to represent the Flywheel hierarchy with specific tree nodes.
Home-page: https://gitlab.com/flywheel-io/scientific-solutions/lib/fw-pyqt-hierarchy-tree-items
License: MIT
Keywords: Flywheel,Libs
Author: Flywheel
Author-email: support@flywheel.io
Requires-Python: >=3.8,<3.11
Classifier: License :: OSI Approved :: MIT License
Classifier: Programming Language :: Python :: 3
Classifier: Programming Language :: Python :: 3.8
Classifier: Programming Language :: Python :: 3.9
Classifier: Programming Language :: Python :: 3.10
Classifier: Topic :: Scientific/Engineering
Requires-Dist: flywheel-sdk (>=17.0,<18.0)
Requires-Dist: importlib-metadata (>=6.8.0,<7.0.0)
Requires-Dist: xmltodict (>=0.13.0,<0.14.0)
Project-URL: Repository, https://gitlab.com/flywheel-io/scientific-solutions/lib/fw-pyqt-hierarchy-tree-items
